<crmcustomfield scriptid="custevent_send_as_email_user">
  <accesslevel>2</accesslevel>
  <appliesperkeyword>F</appliesperkeyword>
  <appliestocampaign>F</appliestocampaign>
  <appliestocase>T</appliestocase>
  <appliestoevent>F</appliestoevent>
  <appliestophonecall>F</appliestophonecall>
  <appliestosolution>F</appliestosolution>
  <appliestotask>F</appliestotask>
  <applyformatting>T</applyformatting>
  <availableexternally>F</availableexternally>
  <checkspelling>F</checkspelling>
  <defaultchecked>F</defaultchecked>
  <defaultselection></defaultselection>
  <defaultvalue></defaultvalue>
  <description></description>
  <displayheight></displayheight>
  <displaytype>NORMAL</displaytype>
  <displaywidth></displaywidth>
  <dynamicdefault></dynamicdefault>
  <encryptatrest>F</encryptatrest>
  <fieldtype>SELECT</fieldtype>
  <globalsearch>F</globalsearch>
  <help></help>
  <isformula>F</isformula>
  <ismandatory>F</ismandatory>
  <isparent>F</isparent>
  <label>Send-As Email User</label>
  <linktext></linktext>
  <maxlength></maxlength>
  <maxvalue></maxvalue>
  <minvalue></minvalue>
  <onparentdelete>SET_NULL</onparentdelete>
  <parentsubtab></parentsubtab>
  <searchcomparefield></searchcomparefield>
  <searchdefault></searchdefault>
  <searchlevel>2</searchlevel>
  <selectrecordtype>-4</selectrecordtype>
  <showhierarchy>F</showhierarchy>
  <showinlist>F</showinlist>
  <sourcefilterby></sourcefilterby>
  <sourcefrom>[scriptid=custentity_send_as_email_user]</sourcefrom>
  <sourcelist>[scriptid=custevent_builder]</sourcelist>
  <storevalue>T</storevalue>
  <subtab></subtab>
</crmcustomfield>