<usereventscript scriptid="customscript_hms_appointment_ue">
  <description></description>
  <isinactive>F</isinactive>
  <name>HMS Appointment UE</name>
  <notifyadmins>F</notifyadmins>
  <notifyemails></notifyemails>
  <notifyowner>T</notifyowner>
  <notifyuser>F</notifyuser>
  <scriptfile>[/SuiteScripts/Projects/hms-case-record/hms_appointment_ue.js]</scriptfile>
  <scriptdeployments>
    <scriptdeployment scriptid="customdeploy_hms_appointment_ue">
      <allemployees>F</allemployees>
      <alllocalizationcontexts>T</alllocalizationcontexts>
      <allpartners>F</allpartners>
      <allroles>F</allroles>
      <audslctrole></audslctrole>
      <eventtype></eventtype>
      <executioncontext>ACTION|ADVANCEDREVREC|BANKCONNECTIVITY|BANKSTATEMENTPARSER|BUNDLEINSTALLATION|CLIENT|CONSOLRATEADJUSTOR|CSVIMPORT|CUSTOMGLLINES|CUSTOMMASSUPDATE|DATASETBUILDER|DEBUGGER|EMAILCAPTURE|FIPARSER|MAPREDUCE|OCRPLUGIN|OTHER|PAYMENTGATEWAY|PAYMENTPOSTBACK|PLATFORMEXTENSION|PORTLET|PROMOTIONS|RECORDACTION|RESTLET|SCHEDULED|SDFINSTALLATION|SHIPPINGPARTNERS|SUITELET|TAXCALCULATION|USEREVENT|USERINTERFACE|WEBAPPLICATION|WEBSERVICES|WORKBOOKBUILDER|WORKFLOW</executioncontext>
      <isdeployed>F</isdeployed>
      <loglevel>DEBUG</loglevel>
      <recordtype>SUPPORTCASE</recordtype>
      <runasrole></runasrole>
      <status>TESTING</status>
    </scriptdeployment>
  </scriptdeployments>
</usereventscript>