<scheduledscript scriptid="customscript_mw_csv_report_import">
  <description></description>
  <isinactive>F</isinactive>
  <name>CSV Report Import</name>
  <notifyadmins>F</notifyadmins>
  <notifyemails></notifyemails>
  <notifyowner>T</notifyowner>
  <scriptfile>[/SuiteScripts/Midware/PropertyImportTool/ScheduledScripts/CSVReportImport.js]</scriptfile>
  <scriptcustomfields>
    <scriptcustomfield scriptid="custscript_mw_working_queue">
      <accesslevel>2</accesslevel>
      <applyformatting>F</applyformatting>
      <checkspelling>F</checkspelling>
      <defaultchecked>F</defaultchecked>
      <defaultselection></defaultselection>
      <defaultvalue></defaultvalue>
      <description></description>
      <displayheight></displayheight>
      <displaytype>NORMAL</displaytype>
      <displaywidth></displaywidth>
      <dynamicdefault></dynamicdefault>
      <fieldtype>SELECT</fieldtype>
      <help></help>
      <isformula>F</isformula>
      <ismandatory>F</ismandatory>
      <label>Working Queue</label>
      <linktext></linktext>
      <maxlength></maxlength>
      <maxvalue></maxvalue>
      <minvalue></minvalue>
      <onparentdelete>NO_ACTION</onparentdelete>
      <searchlevel>2</searchlevel>
      <selectrecordtype>[scriptid=customrecord_mw_import_property_queue]</selectrecordtype>
      <setting></setting>
      <storevalue>T</storevalue>
    </scriptcustomfield>
    <scriptcustomfield scriptid="custscript_mw_index">
      <accesslevel>2</accesslevel>
      <applyformatting>T</applyformatting>
      <checkspelling>F</checkspelling>
      <defaultchecked>F</defaultchecked>
      <defaultselection></defaultselection>
      <defaultvalue></defaultvalue>
      <description></description>
      <displayheight></displayheight>
      <displaytype>NORMAL</displaytype>
      <displaywidth></displaywidth>
      <dynamicdefault></dynamicdefault>
      <fieldtype>INTEGER</fieldtype>
      <help></help>
      <isformula>F</isformula>
      <ismandatory>F</ismandatory>
      <label>Index</label>
      <linktext></linktext>
      <maxlength></maxlength>
      <maxvalue></maxvalue>
      <minvalue></minvalue>
      <onparentdelete></onparentdelete>
      <searchlevel>2</searchlevel>
      <selectrecordtype></selectrecordtype>
      <setting></setting>
      <storevalue>T</storevalue>
    </scriptcustomfield>
    <scriptcustomfield scriptid="custscript_mw_index_s1">
      <accesslevel>2</accesslevel>
      <applyformatting>T</applyformatting>
      <checkspelling>F</checkspelling>
      <defaultchecked>F</defaultchecked>
      <defaultselection></defaultselection>
      <defaultvalue></defaultvalue>
      <description></description>
      <displayheight></displayheight>
      <displaytype>NORMAL</displaytype>
      <displaywidth></displaywidth>
      <dynamicdefault></dynamicdefault>
      <fieldtype>INTEGER</fieldtype>
      <help></help>
      <isformula>F</isformula>
      <ismandatory>F</ismandatory>
      <label>Index Search 1</label>
      <linktext></linktext>
      <maxlength></maxlength>
      <maxvalue></maxvalue>
      <minvalue></minvalue>
      <onparentdelete></onparentdelete>
      <searchlevel>2</searchlevel>
      <selectrecordtype></selectrecordtype>
      <setting></setting>
      <storevalue>T</storevalue>
    </scriptcustomfield>
    <scriptcustomfield scriptid="custscript_mw_index_s2">
      <accesslevel>2</accesslevel>
      <applyformatting>T</applyformatting>
      <checkspelling>F</checkspelling>
      <defaultchecked>F</defaultchecked>
      <defaultselection></defaultselection>
      <defaultvalue></defaultvalue>
      <description></description>
      <displayheight></displayheight>
      <displaytype>NORMAL</displaytype>
      <displaywidth></displaywidth>
      <dynamicdefault></dynamicdefault>
      <fieldtype>INTEGER</fieldtype>
      <help></help>
      <isformula>F</isformula>
      <ismandatory>F</ismandatory>
      <label>Index Search 2</label>
      <linktext></linktext>
      <maxlength></maxlength>
      <maxvalue></maxvalue>
      <minvalue></minvalue>
      <onparentdelete></onparentdelete>
      <searchlevel>2</searchlevel>
      <selectrecordtype></selectrecordtype>
      <setting></setting>
      <storevalue>T</storevalue>
    </scriptcustomfield>
    <scriptcustomfield scriptid="custscript_mw_status">
      <accesslevel>2</accesslevel>
      <applyformatting>F</applyformatting>
      <checkspelling>F</checkspelling>
      <defaultchecked>F</defaultchecked>
      <defaultselection></defaultselection>
      <defaultvalue></defaultvalue>
      <description></description>
      <displayheight></displayheight>
      <displaytype>NORMAL</displaytype>
      <displaywidth></displaywidth>
      <dynamicdefault></dynamicdefault>
      <fieldtype>TEXT</fieldtype>
      <help></help>
      <isformula>F</isformula>
      <ismandatory>F</ismandatory>
      <label>Status Report</label>
      <linktext></linktext>
      <maxlength></maxlength>
      <maxvalue></maxvalue>
      <minvalue></minvalue>
      <onparentdelete></onparentdelete>
      <searchlevel>2</searchlevel>
      <selectrecordtype></selectrecordtype>
      <setting></setting>
      <storevalue>T</storevalue>
    </scriptcustomfield>
  </scriptcustomfields>
  <scriptdeployments>
    <scriptdeployment scriptid="customdeploy_mw_csv_report_import_d">
      <custscript_mw_index>1</custscript_mw_index>
      <custscript_mw_index_s1></custscript_mw_index_s1>
      <custscript_mw_index_s2></custscript_mw_index_s2>
      <custscript_mw_status></custscript_mw_status>
      <custscript_mw_working_queue></custscript_mw_working_queue>
      <isdeployed>T</isdeployed>
      <loglevel>DEBUG</loglevel>
      <status>NOTSCHEDULED</status>
      <title>CSV Report Import</title>
      <recurrence>
        <single>
          <repeat></repeat>
          <startdate>2021-10-29</startdate>
          <starttime>22:00:00Z</starttime>
        </single>
      </recurrence>
    </scriptdeployment>
  </scriptdeployments>
</scheduledscript>